{
    "sports": [
        {
            "label": "football",
            "category": "equipe",
            "difficulty": "intense",
            "description": "Pas de description",
            "rate": 0
        },
        {
            "label": "basketball",
            "category": "equipe",
            "difficulty": "intense",
            "description": "Pas de description",
            "rate": 0
        },
        {
            "label": "baseball",
            "category": "equipe",
            "difficulty": "intense",
            "description": "Pas de description",
            "rate": 0
        },
        {
            "label": "handball",
            "category": "equipe",
            "difficulty": "intense",
            "description": "Pas de description",
            "rate": 0
        },
        {
            "label": "rugby",
            "category": "equipe",
            "difficulty": "intense",
            "description": "Pas de description",
            "rate": 0
        },
        {
            "label": "golf",
            "category": "individuel",
            "difficulty": "relaxant",
            "description": "Pas de description",
            "rate": 0
        },
        {
            "label": "tennis",
            "category": "individuel",
            "difficulty": "intense",
            "description": "Pas de description",
            "rate": 0
        },
        {
            "label": "fitness",
            "category": "equipe::individuel",
            "difficulty": "intense",
            "description": "Pas de description",
            "rate": 0
        },
        {
            "label": "bodybuilding",
            "category": "equipe::individuel",
            "difficulty": "intense",
            "description": "Pas de description",
            "rate": 0
        },
        {
            "label": "cyclisme",
            "category": "equipe::individuel",
            "difficulty": "intense",
            "description": "Pas de description",
            "rate": 0
        }
    ]
}
